pgusers/__init__.py
pgusers/_version.py
pgusers/pgusers.py
pgusers/pgusrmanager.py
pgusers-0.9.4.dist-info/licenses/LICENSE
tests/test_users.py
pgusers-0.9.4.dist-info/METADATA
pgusers-0.9.4.dist-info/WHEEL
pgusers-0.9.4.dist-info/entry_points.txt
pgusers-0.9.4.dist-info/top_level.txt
pgusers-0.9.4.dist-info/RECORD
