Metadata-Version: 2.4
Name: pgusers
Version: 0.9.4
Summary: user and session management on postgresql database
Author-email: Javier Llopis <javier@llopis.me>
License-Expression: MIT
Project-URL: Repository, https://github.com/destrangis/pgusers
Classifier: Development Status :: 4 - Beta
Classifier: Intended Audience :: Developers
Classifier: Operating System :: OS Independent
Classifier: Programming Language :: Python :: 3 :: Only
Classifier: Topic :: Database
Requires-Python: >=3.10
License-File: LICENSE
Requires-Dist: psycopg[binary]
Dynamic: license-file
